openmqttgateway_ble_decoder/__init__.py
openmqttgateway_ble_decoder/ble_parser.py
openmqttgateway_ble_decoder/helpers.py
openmqttgateway_ble_decoder/main.py
openmqttgateway_ble_decoder/xiaomi.py
openmqttgateway_ble_decoder-0.1.1.dist-info/METADATA
openmqttgateway_ble_decoder-0.1.1.dist-info/WHEEL
openmqttgateway_ble_decoder-0.1.1.dist-info/entry_points.txt
openmqttgateway_ble_decoder-0.1.1.dist-info/RECORD
