Metadata-Version: 2.1
Name: openmqttgateway-ble-decoder
Version: 0.1.1
Summary: 
License: WTFPL
Author: kotborealis
Author-email: kotborealis@awooo.ru
Requires-Python: >=3.6,<4.0
Classifier: License :: Other/Proprietary License
Classifier: Programming Language :: Python :: 3
Classifier: Programming Language :: Python :: 3.6
Classifier: Programming Language :: Python :: 3.7
Classifier: Programming Language :: Python :: 3.8
Classifier: Programming Language :: Python :: 3.9
Classifier: Programming Language :: Python :: 3.10
Classifier: Programming Language :: Python :: 3.11
Requires-Dist: click (>=8.1.7,<9.0.0)
Requires-Dist: paho-mqtt (>=1.6.1,<2.0.0)
Requires-Dist: pycryptodome (>=3.19.0,<4.0.0)
Requires-Dist: types-paho-mqtt (>=1.6.0.7,<2.0.0.0)
